txq/__init__.py
txq/apps/__init__.py
txq/apps/app.py
txq/apps/users_app/__init__.py
txq/apps/users_app/users_app.py
txq/apps/users_app/messages/__init__.py
txq/apps/users_app/messages/auth_user_message.py
txq/apps/users_app/messages/create_user_message.py
txq/apps/users_app/messages/update_user_message.py
txq/apps/users_app/messages/verify_token_message.py
txq/apps/users_app/models/__init__.py
txq/apps/users_app/models/user.py
txq/config/__init__.py
txq/config/config.py
txq/pipes/__init__.py
txq/pipes/base_pipe.py
txq/pipes/http_pipe.py
txq/pipes/internal_pipe.py
txq/pipes/nats_pipe.py
txq-0.2.0.dist-info/LICENSE
txq-0.2.0.dist-info/METADATA
txq-0.2.0.dist-info/WHEEL
txq-0.2.0.dist-info/top_level.txt
txq-0.2.0.dist-info/zip-safe
txq-0.2.0.dist-info/RECORD
