Metadata-Version: 2.1
Name: txq
Version: 0.2.0
Summary: Modular asynchronous application service
Home-page: https://github.com/agratoth/txq
Maintainer: Anton Berdnikov
Maintainer-email: agratoth@yandex.ru
License: UNKNOWN
Platform: UNKNOWN
Classifier: License :: OSI Approved :: MIT License
Classifier: Operating System :: OS Independent
Classifier: Programming Language :: Python
Classifier: Programming Language :: Python :: 3.8
Classifier: Programming Language :: Python :: 3.9
Requires-Python: >=3.8
Requires-Dist: PyYAML (>=5.4.1)
Requires-Dist: aiohttp (>=3.7.4)
Requires-Dist: aiojobs (>=0.3.0)
Requires-Dist: asyncio-nats-client (>=0.11.4)
Requires-Dist: nkeys (>=0.1.0)
Requires-Dist: pynsodm (>=0.3.3)
Requires-Dist: txq-messages (>=0.1.0)
Requires-Dist: uvloop (>=0.15.2)
